resource_reporter/__init__.py
resource_reporter/reporter.py
resource_reporter/collectors/__init__.py
resource_reporter/collectors/base.py
resource_reporter/collectors/gpu.py
resource_reporter/collectors/system.py
resource_reporter/utils/__init__.py
resource_reporter/utils/network.py
tests/__init__.py
tests/test_reporter.py
resource_reporter-0.1.3.dist-info/LICENSE
resource_reporter-0.1.3.dist-info/METADATA
resource_reporter-0.1.3.dist-info/WHEEL
resource_reporter-0.1.3.dist-info/top_level.txt
resource_reporter-0.1.3.dist-info/RECORD
