Metadata-Version: 2.2
Name: resource-reporter
Version: 0.1.3
Summary: A comprehensive monitoring library for real-time resource tracking and remote management of containerized applications with support for metrics reporting, asynchronous event notifications, and command listening via Google PubSub
Home-page: https://github.com/yourusername/resource-reporter
Author: QuangLe
Author-email: joneyquang1997@gmail.com
Keywords: monitoring,resource,metrics,pubsub,containers,kubernetes,docker,reporting,distributed,cloud
Classifier: Programming Language :: Python :: 3
Classifier: License :: OSI Approved :: MIT License
Classifier: Operating System :: OS Independent
Classifier: Topic :: System :: Monitoring
Classifier: Topic :: System :: Distributed Computing
Classifier: Topic :: Software Development :: Libraries :: Python Modules
Classifier: Intended Audience :: Developers
Classifier: Intended Audience :: System Administrators
Classifier: Development Status :: 4 - Beta
Requires-Python: >=3.6
License-File: LICENSE
Requires-Dist: requests>=2.25.0
Requires-Dist: psutil>=5.8.0
Requires-Dist: google-cloud-pubsub>=2.0.0
Provides-Extra: gpu
Requires-Dist: pynvml>=11.0.0; extra == "gpu"
Dynamic: author
Dynamic: author-email
Dynamic: classifier
Dynamic: description
Dynamic: description-content-type
Dynamic: home-page
Dynamic: keywords
Dynamic: provides-extra
Dynamic: requires-dist
Dynamic: requires-python
Dynamic: summary
